smartvis/Visualizer.py
smartvis/__init__.py
smartvis-0.0.2.dist-info/METADATA
smartvis-0.0.2.dist-info/WHEEL
smartvis-0.0.2.dist-info/licenses/LICENSE
smartvis-0.0.2.dist-info/RECORD
