Metadata-Version: 2.4
Name: smartvis
Version: 0.0.2
Summary: Package to Visualize Columns Relationships in Ease.
Project-URL: Homepage, https://github.com/Shidhin-VP/SmartVis
Project-URL: Issues, https://github.com/Shidhin-VP/SmartVis/issues
Author: Shidhin Varghese Philip
License-File: LICENSE
Classifier: License :: OSI Approved :: MIT License
Classifier: Operating System :: OS Independent
Classifier: Programming Language :: Python :: 3.10
Requires-Python: >=3.10
Requires-Dist: pandas
Requires-Dist: plotly
